study_da/__init__.py
study_da/assets/__init__.py
study_da/assets/configurations/config_hllhc13.yaml
study_da/assets/configurations/config_hllhc16.yaml
study_da/assets/configurations/config_runIII.yaml
study_da/assets/configurations/config_runIII_ions.yaml
study_da/assets/filling_schemes/25ns_1886b_1873_1217_1173_236bpi_12inj_hybrid_2INDIV.json
study_da/assets/filling_schemes/25ns_1886b_1873_1217_1173_236bpi_12inj_hybrid_2INDIV_converted.json
study_da/assets/filling_schemes/25ns_1983b_1970_1657_1684_144bpi_19inj_3INDIVs.json
study_da/assets/filling_schemes/25ns_1983b_1970_1657_1684_144bpi_19inj_3INDIVs_converted.json
study_da/assets/filling_schemes/25ns_2076b_2064_1327_1928_216bpi_12inj_800ns_bs200ns.json
study_da/assets/filling_schemes/25ns_2076b_2064_1327_1928_216bpi_12inj_800ns_bs200ns_with_identical_bunches.json
study_da/assets/filling_schemes/25ns_2228b_2216_1686_2112_hybrid_8b4e_2x56b_25ns_3x48b_12inj.json
study_da/assets/filling_schemes/25ns_2228b_2216_1686_2112_hybrid_8b4e_2x56b_25ns_3x48b_12inj_with_identical_bunches.json
study_da/assets/filling_schemes/25ns_2358b_2345_1692_1628_236bpi_14inj_hybrid_2INDIV.json
study_da/assets/filling_schemes/25ns_2358b_2345_1692_1628_236bpi_14inj_hybrid_2INDIV_converted.json
study_da/assets/filling_schemes/25ns_2374b_2361_1730_1773_236bpi_13inj_hybrid_2INDIV.json
study_da/assets/filling_schemes/25ns_2374b_2361_1730_1773_236bpi_13inj_hybrid_2INDIV_converted.json
study_da/assets/filling_schemes/25ns_2374b_2361_1730_1773_236bpi_13inj_hybrid_2INDIV_converted_with_identical_bunches.json
study_da/assets/filling_schemes/25ns_2464b_2452_1842_1821_236bpi_12inj_hybrid copy.json
study_da/assets/filling_schemes/25ns_2464b_2452_1842_1821_236bpi_12inj_hybrid.json
study_da/assets/filling_schemes/25ns_2464b_2452_1842_1821_236bpi_12inj_hybrid_converted.json
study_da/assets/filling_schemes/25ns_2464b_2452_1842_1821_236bpi_12inj_hybrid_converted_with_identical_bunches.json
study_da-0.5.3.dist-info/LICENSE
study_da-0.5.3.dist-info/METADATA
study_da-0.5.3.dist-info/WHEEL
study_da-0.5.3.dist-info/RECORD
