Metadata-Version: 2.1
Name: study-da
Version: 0.5.3
Summary: A tool to create and submit large-scale DA simulations.
Author: Colas
Author-email: colasdroin@gmail.com
Requires-Python: >=3.11,<3.13
Classifier: Programming Language :: Python :: 3
Classifier: Programming Language :: Python :: 3.11
Classifier: Programming Language :: Python :: 3.12
Requires-Dist: black (>=24.10.0,<25.0.0)
Requires-Dist: cpymad (>=1.16.3,<2.0.0)
Requires-Dist: fastparquet (>=2024.11.0,<2025.0.0)
Requires-Dist: filelock (>=3.16.1,<4.0.0)
Requires-Dist: ipython (>=8.29.0,<9.0.0)
Requires-Dist: jinja2 (>=3.1.4,<4.0.0)
Requires-Dist: llvmlite (>=0.43.0,<0.44.0)
Requires-Dist: matplotlib (>=3.9.2,<4.0.0)
Requires-Dist: matplotlib-inline (>=0.1.7,<0.2.0)
Requires-Dist: nafflib (>=2.0.2,<3.0.0)
Requires-Dist: numba (>=0.60.0,<0.61.0)
Requires-Dist: numpy (>=2.0.2,<3.0.0)
Requires-Dist: pandas (>=2.2.3,<3.0.0)
Requires-Dist: psutil (>=6.1.0,<7.0.0)
Requires-Dist: pyyaml (>=6.0.2,<7.0.0)
Requires-Dist: qrcode (>=8.0,<9.0)
Requires-Dist: ruamel-yaml (>=0.18.6,<0.19.0)
Requires-Dist: seaborn (>=0.13.2,<0.14.0)
Requires-Dist: xsuite (>=0.18.10,<0.19.0)
